src/__init__.py
src/cli.py
xopera_template_library-0.2.3.dist-info/LICENSE
xopera_template_library-0.2.3.dist-info/METADATA
xopera_template_library-0.2.3.dist-info/WHEEL
xopera_template_library-0.2.3.dist-info/entry_points.txt
xopera_template_library-0.2.3.dist-info/top_level.txt
xopera_template_library-0.2.3.dist-info/zip-safe
xopera_template_library-0.2.3.dist-info/RECORD
