Metadata-Version: 2.1
Name: xopera-template-library
Version: 0.2.3
Summary: Python CLI for managing template library.
Home-page: https://gitlab.xlab.si/radon/template-library-cli/-/tree/pypi
Author: XLAB d.o.o.
Author-email: pypi@xlab.si
License: UNKNOWN
Project-URL: Source Code, https://gitlab.xlab.si/radon/template-library-cli/-/tree/pypi
Project-URL: Bug Tracker, https://gitlab.xlab.si/radon/template-library-cli/-/issues
Keywords: radon,templates,library,artifact,particles
Platform: UNKNOWN
Classifier: Development Status :: 2 - Pre-Alpha
Classifier: Environment :: Console
Classifier: Intended Audience :: Developers
Classifier: Intended Audience :: System Administrators
Classifier: License :: OSI Approved :: Apache Software License
Classifier: Operating System :: OS Independent
Classifier: Programming Language :: Python
Classifier: Programming Language :: Python :: 3
Classifier: Programming Language :: Python :: 3.6
Classifier: Programming Language :: Python :: 3.7
Requires-Dist: gitpython (==3.1.0)
Requires-Dist: PyYAML (==5.3)
Requires-Dist: psycopg2-binary (==2.8.4)
Requires-Dist: requests (==2.23.0)
Requires-Dist: requests-toolbelt (==0.9.1)
Requires-Dist: outdated (>=0.2.1)
Requires-Dist: scutils (==1.2.0)
Requires-Dist: terminaltables (==3.1.0)
Requires-Dist: lxml (==4.5.2)
